Metadata-Version: 1.1
Name: fsbotlogin
Version: 0.0.1
Summary: A simple auto-login bot using python
Home-page: UNKNOWN
Author: Akash Jha
Author-email: ajha@fleetstudio.com
License: MIT
Keywords: botlogin
Platform: UNKNOWN
Classifier: Development Status :: 5 - Production/Stable
Classifier: Intended Audience :: Education
Classifier: Operating System :: Microsoft :: Windows :: Windows 10
Classifier: License :: OSI Approved :: MIT License
Classifier: Programming Language :: Python :: 3
